autoray/__init__.py
autoray/_version.py
autoray/autoray.py
autoray/compiler.py
autoray/experimental/__init__.py
autoray/experimental/complexity_tracing.py
autoray/experimental/complexity_tracing_example.ipynb
autoray/lazy/__init__.py
autoray/lazy/core.py
autoray/lazy/draw.py
autoray/lazy/linalg.py
autoray-0.7.0.dist-info/LICENSE
autoray-0.7.0.dist-info/METADATA
autoray-0.7.0.dist-info/WHEEL
autoray-0.7.0.dist-info/top_level.txt
autoray-0.7.0.dist-info/RECORD
