Metadata-Version: 2.1
Name: autoray
Version: 0.7.0
Summary: Abstract your array operations.
Author-email: Johnnie Gray <johnniemcgray@gmail.com>
License: Apache
Project-URL: Documentation, https://autoray.readthedocs.io/
Project-URL: Repository, https://github.com/jcmgray/autoray/
Project-URL: Issues, https://github.com/jcmgray/autoray/issues
Project-URL: Changelog, https://github.com/jcmgray/autoray/releases
Keywords: agnostic,array,autograd,cupy,dask,dispatch,jax,numeric,numpy,tensor,tensorflow
Classifier: Development Status :: 3 - Alpha
Classifier: License :: OSI Approved :: Apache Software License
Classifier: Programming Language :: Python :: 3
Classifier: Programming Language :: Python :: 3.9
Classifier: Programming Language :: Python :: 3.10
Classifier: Programming Language :: Python :: 3.11
Classifier: Programming Language :: Python :: 3.12
Requires-Python: >=3.9
License-File: LICENSE
Provides-Extra: tests
Requires-Dist: numpy; extra == "tests"
Requires-Dist: coverage; extra == "tests"
Requires-Dist: pytest; extra == "tests"
Requires-Dist: pytest-cov; extra == "tests"
Provides-Extra: docs
Requires-Dist: astroid<3; extra == "docs"
Requires-Dist: furo; extra == "docs"
Requires-Dist: ipython!=8.7.0; extra == "docs"
Requires-Dist: myst-nb; extra == "docs"
Requires-Dist: setuptools_scm; extra == "docs"
Requires-Dist: sphinx-autoapi; extra == "docs"
Requires-Dist: sphinx-copybutton; extra == "docs"
Requires-Dist: sphinx>=2.0; extra == "docs"
